LICENSE
MANIFEST.in
README.md
setup.py
yamo/__init__.py
yamo/cache.py
yamo/connection.py
yamo/document.py
yamo/errors.py
yamo/fields.py
yamo/metatype.py
yamo.egg-info/PKG-INFO
yamo.egg-info/SOURCES.txt
yamo.egg-info/dependency_links.txt
yamo.egg-info/requires.txt
yamo.egg-info/top_level.txt