Metadata-Version: 1.1
Name: yamo
Version: 0.2.23
Summary: Yet Another MongoDB ORM
Home-page: https://github.com/observerss/yamo
Author: Jingchao Hu(observerss)
Author-email: jingchaohu@gmail.com
License: The MIT License (MIT)
